lsf_prometheus_exporter/__init__.py
lsf_prometheus_exporter/__main__.py
lsf_prometheus_exporter/lsf_prometheus_exporter.py
lsf_prometheus_exporter/cmdline_collectors/__init__.py
lsf_prometheus_exporter/cmdline_collectors/badmin_collector.py
lsf_prometheus_exporter/cmdline_collectors/bhosts_collector.py
lsf_prometheus_exporter/cmdline_collectors/bqueues_collector.py
lsf_prometheus_exporter/cmdline_collectors/lsid_collector.py
lsf_prometheus_exporter/cmdline_collectors/lsload_collector.py
lsf_prometheus_exporter/lib_collectors/__init__.py
lsf_prometheus_exporter/lib_collectors/psutil_collector.py
lsf_prometheus_exporter/metrics_utils/__init__.py
lsf_prometheus_exporter/metrics_utils/utils.py
lsf_prometheus_exporter-1.0.1.dist-info/licenses/LICENSE
lsf_prometheus_exporter-1.0.1.dist-info/METADATA
lsf_prometheus_exporter-1.0.1.dist-info/WHEEL
lsf_prometheus_exporter-1.0.1.dist-info/entry_points.txt
lsf_prometheus_exporter-1.0.1.dist-info/top_level.txt
lsf_prometheus_exporter-1.0.1.dist-info/RECORD
