Metadata-Version: 2.4
Name: lsf_prometheus_exporter
Version: 1.0.1
Summary: LSF Prometheus Exporter
Author-email: IBM Spectrum Computing <spectrum_lsf_support@ca.ibm.com>
License-Expression: Apache-2.0
Keywords: HPC, LSF, IBM
Classifier: Programming Language :: Python :: 3.11
Classifier: Operating System :: OS Independent
Classifier: Development Status :: 5 - Production/Stable
Classifier: Intended Audience :: System Administrators
Requires-Python: >=3.11
License-File: LICENSE
Requires-Dist: prometheus_client>=0.21.1
Requires-Dist: psutil>=6.1.1
Dynamic: license-file
